{"1":{"w":[{"b":"0.44","h":"0.55","c":"الٓمٓ","d":"alif-lam-meem","e":"Alif Lam Mim"}],"a":{"g":"Alif, Lam, Meem."}},"2":{"w":[{"b":"0.34","h":"0","c":"غُلِبَتِ","d":"ghulibati","e":"Have been defeated"},{"b":"1.0","h":"0","c":"الرُّومُ","d":"l-rūmu","e":"the Romans"}],"a":{"g":"The Byzantines have been defeated"}},"3":{"w":[{"b":"0.11","h":"0.45","c":"فِي","d":"fī","e":"In"},{"b":"2.1","h":"2.42","c":"أَدْنَى","d":"adnā","e":"(the) nearest"},{"b":"2.7","h":"3.41","c":"الْأَرْضِ","d":"l-arḍi","e":"land"},{"b":"3.7","h":"4.9","c":"وَهُمْ","d":"wahum","e":"But they"},{"b":"5.0","h":"6.57","c":"مِنْ","d":"min","e":"after"},{"b":"5.8","h":"7.61","c":"بَعْدِ","d":"baʿdi","e":"after"},{"b":"6.4","h":"8.58","c":"غَلَبِهِمْ","d":"ghalabihim","e":"their defeat"},{"b":"7.4","h":"10.33","c":"سَيَغْلِبُونَ","d":"sayaghlibūna","e":"will overcome"}],"a":{"g":"In the nearest land. But they, after their defeat, will overcome."}},"4":{"w":[{"b":"0.1","h":"1.05","c":"فِي","d":"fī","e":"Within"},{"b":"0.52","h":"1.62","c":"بِضْعِ","d":"biḍ'ʿi","e":"a few"},{"b":"1.1","h":"2.71","c":"سِنِينَ","d":"sinīna","e":"years"},{"b":"4.1","h":"4.82","c":"لِلَّهِ","d":"lillahi","e":"For Allah"},{"b":"5.2","h":"8.72","c":"الْأَمْرُ","d":"l-amru","e":"(is) the command"},{"b":"6.0","h":"10.24","c":"مِنْ","d":"min","e":"before"},{"b":"7.1","h":"11.47","c":"قَبْلُ","d":"qablu","e":"before"},{"b":"7.8","h":"12.65","c":"وَمِنْ","d":"wamin","e":"and after"},{"b":"9.2","h":"14.38","c":"بَعْدُ","d":"baʿdu","e":"and after"},{"b":"10.2","h":"18.05","c":"وَيَوْمَئِذٍ","d":"wayawma-idhin","e":"And that day"},{"b":"12.1","h":"20.68","c":"يَفْرَحُ","d":"yafraḥu","e":"will rejoice"},{"b":"13","h":"22.23","c":"الْمُؤْمِنُونَ","d":"l-mu'minūna","e":"the believers"}],"a":{"g":"Within three to nine years. To Allah belongs the command before and after. And that day the believers will rejoice"}},"5":{"w":[{"b":"0.23","h":"0.65","c":"بِنَصْرِ","d":"binaṣri","e":"With (the) help"},{"b":"1.2","h":"2.02","c":"اللَّهِ","d":"l-lahi","e":"(of) Allah"},{"b":"4.0","h":"6.1","c":"يَنْصُرُ","d":"yanṣuru","e":"He helps"},{"b":"5.7","h":"8.1","c":"مَنْ","d":"man","e":"whom"},{"b":"6.8","h":"9.44","c":"يَشَاءُ","d":"yashāu","e":"He wills"},{"b":"9.3","h":"14.35","c":"وَهُوَ","d":"wahuwa","e":"And He"},{"b":"9.9","h":"15.24","c":"الْعَزِيزُ","d":"l-ʿazīzu","e":"(is) the All-Mighty"},{"b":"11.0","h":"17.21","c":"الرَّحِيمُ","d":"l-raḥīmu","e":"the Most Merciful"}],"a":{"g":"In the victory of Allah. He gives victory to whom He wills, and He is the Exalted in Might, the Merciful."}},"6":{"w":[{"b":"0.2","h":"0.72","c":"وَعْدَ","d":"waʿda","e":"(It is the) Promise"},{"b":"0.85","h":"1.76","c":"اللَّهِ","d":"l-lahi","e":"(of) Allah"},{"b":"4.0","h":"5.8","c":"لَا","d":"lā","e":"(Does) not"},{"b":"4.4","h":"6.55","c":"يُخْلِفُ","d":"yukh'lifu","e":"fail"},{"b":"5.4","h":"8.13","c":"اللَّهُ","d":"l-lahu","e":"Allah"},{"b":"6.2","h":"9.67","c":"وَعْدَهُ","d":"waʿdahu","e":"(in) His promise"},{"b":"7.2","h":"11.6","c":"وَلَكِنَّ","d":"walākinna","e":"but"},{"b":"9.3","h":"14.15","c":"أَكْثَرَ","d":"akthara","e":"most (of)"},{"b":"10.1","h":"15.64","c":"النَّاسِ","d":"l-nāsi","e":"[the] people"},{"b":"11.8","h":"17.63","c":"لَا","d":"lā","e":"(do) not"},{"b":"12.2","h":"18.52","c":"يَعْلَمُونَ","d":"yaʿlamūna","e":"know"}],"a":{"g":"[It is] the promise of Allah. Allah does not fail in His promise, but most of the people do not know."}},"7":{"w":[{"b":"0.22","h":"0.45","c":"يَعْلَمُونَ","d":"yaʿlamūna","e":"They know"},{"b":"1.4","h":"2.45","c":"ظَاهِرًا","d":"ẓāhiran","e":"(the) apparent"},{"b":"3.2","h":"4.99","c":"مِنَ","d":"mina","e":"of"},{"b":"3.5","h":"5.54","c":"الْحَيَوةِ","d":"l-ḥayati","e":"the life"},{"b":"4.6","h":"7.41","c":"الدُّنْيَا","d":"l-dun'yā","e":"(of) the world"},{"b":"5.7","h":"9.31","c":"وَهُمْ","d":"wahum","e":"but they"},{"b":"6.3","h":"10.32","c":"عَنِ","d":"ʿani","e":"about"},{"b":"6.8","h":"11.05","c":"الْءَاخِرَةِ","d":"l-ākhirati","e":"the Hereafter"},{"b":"8.0","h":"13.38","c":"هُمْ","d":"hum","e":"[they]"},{"b":"8.4","h":"14.14","c":"غَافِلُونَ","d":"ghāfilūna","e":"(are) heedless"}],"a":{"g":"They know what is apparent of the worldly life, but they, of the Hereafter, are unaware."}},"8":{"w":[{"b":"0.13","h":"0.3","c":"أَوَلَمْ","d":"awalam","e":"Do not"},{"b":"0.92","h":"1.29","c":"يَتَفَكَّرُوا","d":"yatafakkarū","e":"they ponder"},{"b":"2.3","h":"4.12","c":"فِي","d":"fī","e":"within"},{"b":"2.5","h":"6.03","c":"أَنْفُسِهِمْ","d":"anfusihim","e":"themselves"},{"b":"7.1","h":"10.59","c":"مَا","d":"mā","e":"Not"},{"b":"7.4","h":"11.17","c":"خَلَقَ","d":"khalaqa","e":"Allah (has) created"},{"b":"8.2","h":"12.35","c":"اللَّهُ","d":"l-lahu","e":"Allah (has) created"},{"b":"9","h":"13.83","c":"السَّمَاوَاتِ","d":"l-samāwāti","e":"the heavens"},{"b":"10.5","h":"16.41","c":"وَالْأَرْضَ","d":"wal-arḍa","e":"and the earth"},{"b":"11.6","h":"18.11","c":"وَمَا","d":"wamā","e":"and what"},{"b":"12.2","h":"19.33","c":"بَيْنَهُمَا","d":"baynahumā","e":"(is) between them"},{"b":"15.0","h":"21.01","c":"إِلَّا","d":"illā","e":"except"},{"b":"15.9","h":"24.41","c":"بِالْحَقِّ","d":"bil-ḥaqi","e":"in truth"},{"b":"16.9","h":"26.27","c":"وَأَجَلٍ","d":"wa-ajalin","e":"and (for) a term"},{"b":"18.7","h":"28.69","c":"مُسَمًّى","d":"musamman","e":"appointed"},{"b":"21.3","h":"33.43","c":"وَإِنَّ","d":"wa-inna","e":"And indeed"},{"b":"22.8","h":"35.05","c":"كَثِيرًا","d":"kathīran","e":"many"},{"b":"23.7","h":"36.69","c":"مِنَ","d":"mina","e":"of"},{"b":"25.3","h":"38.36","c":"النَّاسِ","d":"l-nāsi","e":"the people"},{"b":"27.0","h":"40.55","c":"بِلِقَاءِ","d":"biliqāi","e":"in (the) meeting"},{"b":"29.6","h":"43.73","c":"رَبِّهِمْ","d":"rabbihim","e":"(with) their Lord"},{"b":"30.","h":"45.65","c":"لَكَافِرُونَ","d":"lakāfirūna","e":"surely (are) disbelievers"}],"a":{"g":"Do they not contemplate within themselves? Allah has not created the heavens and the earth and what is between them except in truth and for a specified term. And indeed, many of the people, in [the matter of] the meeting with their Lord, are disbelievers."}},"9":{"w":[{"b":"0.2","h":"0.2","c":"أَوَلَمْ","d":"awalam","e":"Have not"},{"b":"0.95","h":"1.3","c":"يَسِيرُوا","d":"yasīrū","e":"they traveled"},{"b":"2.0","h":"3.24","c":"فِي","d":"fī","e":"in"},{"b":"2.3","h":"3.68","c":"الْأَرْضِ","d":"l-arḍi","e":"the earth"},{"b":"3.1","h":"4.97","c":"فَيَنْظُرُوا","d":"fayanẓurū","e":"and observed"},{"b":"5.0","h":"7.61","c":"كَيْفَ","d":"kayfa","e":"how"},{"b":"5.6","h":"8.66","c":"كَانَ","d":"kāna","e":"was"},{"b":"6.2","h":"9.68","c":"عَاقِبَةُ","d":"ʿāqibatu","e":"(the) end"},{"b":"7.4","h":"11.59","c":"الَّذِينَ","d":"alladhīna","e":"(of) those"},{"b":"8.4","h":"13.29","c":"مِنْ","d":"min","e":"before them"},{"b":"9.5","h":"14.49","c":"قَبْلِهِمْ","d":"qablihim","e":"before them"},{"b":"11.","h":"18.2","c":"كَانُوا","d":"kānū","e":"They were"},{"b":"13.5","h":"20.69","c":"أَشَدَّ","d":"ashadda","e":"mightier"},{"b":"14.4","h":"22.13","c":"مِنْهُمْ","d":"min'hum","e":"to them"},{"b":"15.3","h":"23.58","c":"قُوَّةً","d":"quwwatan","e":"(in) strength"},{"b":"16.2","h":"25.8","c":"وَأَثَارُوا","d":"wa-athārū","e":"and they dug"},{"b":"18.2","h":"27.86","c":"الْأَرْضَ","d":"l-arḍa","e":"the earth"},{"b":"19.0","h":"29.27","c":"وَعَمَرُوهَا","d":"waʿamarūhā","e":"and built (on) it"},{"b":"20.2","h":"31.44","c":"أَكْثَرَ","d":"akthara","e":"more"},{"b":"22.5","h":"34.58","c":"مِمَّا","d":"mimmā","e":"than what"},{"b":"23.8","h":"36.25","c":"عَمَرُوهَا","d":"ʿamarūhā","e":"they have built (on) it"},{"b":"25.2","h":"38.84","c":"وَجَاءَتْهُمْ","d":"wajāathum","e":"And came (to) them"},{"b":"28.","h":"42.56","c":"رُسُلُهُمْ","d":"rusuluhum","e":"their Messengers"},{"b":"34.6","h":"44.89","c":"بِالْبَيِّنَاتِ","d":"bil-bayināti","e":"with clear proofs"},{"b":"36.3","h":"50.6","c":"فَمَا","d":"famā","e":"So not"},{"b":"36.9","h":"51.37","c":"كَانَ","d":"kāna","e":"was"},{"b":"37.6","h":"52.59","c":"اللَّهُ","d":"l-lahu","e":"Allah"},{"b":"38.6","h":"54.05","c":"لِيَظْلِمَهُمْ","d":"liyaẓlimahum","e":"to wrong them"},{"b":"44.3","h":"56.41","c":"وَلَكِنْ","d":"walākin","e":"but"},{"b":"46.0","h":"58.67","c":"كَانُوا","d":"kānū","e":"they were"},{"b":"48.5","h":"61.37","c":"أَنْفُسَهُمْ","d":"anfusahum","e":"themselves"},{"b":"50.3","h":"63.93","c":"يَظْلِمُونَ","d":"yaẓlimūna","e":"(doing) wrong"}],"a":{"g":"Have they not traveled through the earth and observed how was the end of those before them? They were greater than them in power, and they plowed the earth and built it up more than they have built it up, and their messengers came to them with clear evidences. And Allah would not ever have wronged them, but they were wronging themselves."}},"10":{"w":[{"b":"0.36","h":"0.6","c":"ثُمَّ","d":"thumma","e":"Then"},{"b":"1.7","h":"1.91","c":"كَانَ","d":"kāna","e":"was"},{"b":"2.3","h":"3.01","c":"عَاقِبَةَ","d":"ʿāqibata","e":"(the) end"},{"b":"3.5","h":"4.87","c":"الَّذِينَ","d":"alladhīna","e":"(of) those who"},{"b":"4.5","h":"6.65","c":"أَسَاءُوا","d":"asāū","e":"did evil"},{"b":"7.1","h":"9.08","c":"السُّوأَى","d":"l-sūā","e":"the evil"},{"b":"11.","h":"11.38","c":"أَنْ","d":"an","e":"because"},{"b":"13.2","h":"14.17","c":"كَذَّبُوا","d":"kadhabū","e":"they denied"},{"b":"14.3","h":"16.13","c":"بِءَايَاتِ","d":"biāyāti","e":"(the) Signs"},{"b":"15.7","h":"18.44","c":"اللَّهِ","d":"l-lahi","e":"(of) Allah"},{"b":"16.6","h":"19.88","c":"وَكَانُوا","d":"wakānū","e":"and were"},{"b":"17.7","h":"21.79","c":"بِهَا","d":"bihā","e":"of them"},{"b":"18.3","h":"22.96","c":"يَسْتَهْزِءُونَ","d":"yastahziūna","e":"making mockery"}],"a":{"g":"Then the end of those who did evil was the worst [consequence] because they denied the signs of Allah and used to ridicule them."}},"11":{"w":[{"b":"0.34","h":"0.5","c":"اللَّهُ","d":"al-lahu","e":"Allah"},{"b":"1.3","h":"2.05","c":"يَبْدَؤُا","d":"yabda-u","e":"originates"},{"b":"2.2","h":"3.34","c":"الْخَلْقَ","d":"l-khalqa","e":"the creation"},{"b":"3.0","h":"4.69","c":"ثُمَّ","d":"thumma","e":"then"},{"b":"4.3","h":"6.15","c":"يُعِيدُهُ","d":"yuʿīduhu","e":"He repeats it"},{"b":"5.6","h":"8.31","c":"ثُمَّ","d":"thumma","e":"then"},{"b":"7.2","h":"9.89","c":"إِلَيْهِ","d":"ilayhi","e":"to Him"},{"b":"8.1","h":"11.34","c":"تُرْجَعُونَ","d":"tur'jaʿūna","e":"you will be returned"}],"a":{"g":"Allah begins creation; then He will repeat it; then to Him you will be returned."}},"12":{"w":[{"b":"0.24","h":"0.25","c":"وَيَوْمَ","d":"wayawma","e":"And (the) Day"},{"b":"1.0","h":"1.47","c":"تَقُومُ","d":"taqūmu","e":"will (be) established"},{"b":"1.9","h":"3.07","c":"السَّاعَةُ","d":"l-sāʿatu","e":"the Hour"},{"b":"2.9","h":"4.96","c":"يُبْلِسُ","d":"yub'lisu","e":"will (be in) despair"},{"b":"3.8","h":"6.32","c":"الْمُجْرِمُونَ","d":"l-muj'rimūna","e":"the criminals"}],"a":{"g":"And the Day the Hour appears the criminals will be in despair."}},"13":{"w":[{"b":"0.07","h":"0.38","c":"وَلَمْ","d":"walam","e":"And not"},{"b":"0.62","h":"1.14","c":"يَكُنْ","d":"yakun","e":"will be"},{"b":"1.0","h":"2.04","c":"لَهُمْ","d":"lahum","e":"for them"},{"b":"2.5","h":"3.97","c":"مِنْ","d":"min","e":"among"},{"b":"3.4","h":"4.86","c":"شُرَكَائِهِمْ","d":"shurakāihim","e":"theirs partners"},{"b":"6.7","h":"8.48","c":"شُفَعَؤُا","d":"shufaʿāu","e":"any intercessors"},{"b":"9.3","h":"11.17","c":"وَكَانُوا","d":"wakānū","e":"and they will be"},{"b":"10.3","h":"12.94","c":"بِشُرَكَائِهِمْ","d":"bishurakāihim","e":"in their partners"},{"b":"13.4","h":"16.57","c":"كَافِرِينَ","d":"kāfirīna","e":"disbelievers"}],"a":{"g":"And there will not be for them among their [alleged] partners any intercessors, and they will [then] be disbelievers in their partners."}},"14":{"w":[{"b":"0.24","h":"0.76","c":"وَيَوْمَ","d":"wayawma","e":"And (the) Day"},{"b":"0.99","h":"1.86","c":"تَقُومُ","d":"taqūmu","e":"will (be) established"},{"b":"1.8","h":"3.43","c":"السَّاعَةُ","d":"l-sāʿatu","e":"the Hour"},{"b":"2.9","h":"5.24","c":"يَوْمَئِذٍ","d":"yawma-idhin","e":"that Day"},{"b":"5.2","h":"7.75","c":"يَتَفَرَّقُونَ","d":"yatafarraqūna","e":"they will become separated"}],"a":{"g":"And the Day the Hour appears - that Day they will become separated."}},"15":{"w":[{"b":"0.2","h":"0.35","c":"فَأَمَّا","d":"fa-ammā","e":"Then as for"},{"b":"2.1","h":"1.84","c":"الَّذِينَ","d":"alladhīna","e":"those who"},{"b":"3.2","h":"3.55","c":"ءَامَنُوا","d":"āmanū","e":"believed"},{"b":"4.3","h":"5.5","c":"وَعَمِلُوا","d":"waʿamilū","e":"and did"},{"b":"5.1","h":"6.77","c":"الصَّالِحَاتِ","d":"l-ṣāliḥāti","e":"righteous deeds"},{"b":"6.6","h":"9.27","c":"فَهُمْ","d":"fahum","e":"so they"},{"b":"7.2","h":"10.36","c":"فِي","d":"fī","e":"in"},{"b":"7.6","h":"11.17","c":"رَوْضَةٍ","d":"rawḍatin","e":"a Garden"},{"b":"9.6","h":"13.57","c":"يُحْبَرُونَ","d":"yuḥ'barūna","e":"will be delighted"}],"a":{"g":"And as for those who had believed and done righteous deeds, they will be in a garden [of Paradise], delighted."}},"16":{"w":[{"b":"0.16","h":"0.82","c":"وَأَمَّا","d":"wa-ammā","e":"But as for"},{"b":"1.7","h":"2.37","c":"الَّذِينَ","d":"alladhīna","e":"those who"},{"b":"2.8","h":"4.06","c":"كَفَرُوا","d":"kafarū","e":"disbelieved"},{"b":"3.6","h":"5.79","c":"وَكَذَّبُوا","d":"wakadhabū","e":"and denied"},{"b":"4.9","h":"7.86","c":"بِءَايَاتِنَا","d":"biāyātinā","e":"Our Signs"},{"b":"6.6","h":"10.82","c":"وَلِقَاءِ","d":"waliqāi","e":"and (the) meeting"},{"b":"9.3","h":"13.6","c":"الْءَاخِرَةِ","d":"l-ākhirati","e":"(of) the Hereafter"},{"b":"10.5","h":"15.8","c":"فَأُولَئِكَ","d":"fa-ulāika","e":"then those"},{"b":"13.2","h":"19.14","c":"فِي","d":"fī","e":"in"},{"b":"13.4","h":"19.61","c":"الْعَذَابِ","d":"l-ʿadhābi","e":"the punishment"},{"b":"14.5","h":"21.61","c":"مُحْضَرُونَ","d":"muḥ'ḍarūna","e":"(will be) brought forth"}],"a":{"g":"But as for those who disbelieved and denied Our verses and the meeting of the Hereafter, those will be brought into the punishment [to remain]."}},"17":{"w":[{"b":"0.18","h":"0.45","c":"فَسُبْحَانَ","d":"fasub'ḥāna","e":"So glory be to"},{"b":"1.4","h":"2.52","c":"اللَّهِ","d":"l-lahi","e":"Allah"},{"b":"2.2","h":"4.07","c":"حِينَ","d":"ḥīna","e":"when"},{"b":"2.8","h":"5.21","c":"تُمْسُونَ","d":"tum'sūna","e":"you reach the evening"},{"b":"3.9","h":"7.25","c":"وَحِينَ","d":"waḥīna","e":"and when"},{"b":"4.7","h":"8.75","c":"تُصْبِحُونَ","d":"tuṣ'biḥūna","e":"you reach the morning"}],"a":{"g":"So exalted is Allah when you reach the evening and when you reach the morning."}},"18":{"w":[{"b":"0.21","h":"0.66","c":"وَلَهُ","d":"walahu","e":"And for Him"},{"b":"0.78","h":"1.66","c":"الْحَمْدُ","d":"l-ḥamdu","e":"(are) all praises"},{"b":"1.5","h":"3","c":"فِي","d":"fī","e":"in"},{"b":"1.8","h":"3.39","c":"السَّمَاوَاتِ","d":"l-samāwāti","e":"the heavens"},{"b":"3.3","h":"6.16","c":"وَالْأَرْضِ","d":"wal-arḍi","e":"and the earth"},{"b":"4.3","h":"7.97","c":"وَعَشِيًّا","d":"waʿashiyyan","e":"and (at) night"},{"b":"5.3","h":"10.04","c":"وَحِينَ","d":"waḥīna","e":"and when"},{"b":"6.9","h":"12.24","c":"تُظْهِرُونَ","d":"tuẓ'hirūna","e":"you are at noon"}],"a":{"g":"And to Him is [due all] praise throughout the heavens and the earth. And [exalted is He] at night and when you are at noon."}},"19":{"w":[{"b":"0.31","h":"0.65","c":"يُخْرِجُ","d":"yukh'riju","e":"He brings forth"},{"b":"1.1","h":"1.86","c":"الْحَيَّ","d":"l-ḥaya","e":"the living"},{"b":"1.9","h":"3.23","c":"مِنَ","d":"mina","e":"from"},{"b":"2.3","h":"3.89","c":"الْمَيِّتِ","d":"l-mayiti","e":"the dead"},{"b":"3.4","h":"5.74","c":"وَيُخْرِجُ","d":"wayukh'riju","e":"and He brings forth"},{"b":"4.3","h":"7.56","c":"الْمَيِّتَ","d":"l-mayita","e":"the dead"},{"b":"5.4","h":"9.34","c":"مِنَ","d":"mina","e":"from"},{"b":"5.7","h":"9.96","c":"الْحَيِّ","d":"l-ḥayi","e":"the living"},{"b":"6.6","h":"11.43","c":"وَيُحْيِي","d":"wayuḥ'yī","e":"and He gives life"},{"b":"7.4","h":"12.89","c":"الْأَرْضَ","d":"l-arḍa","e":"(to) the earth"},{"b":"8.2","h":"14.3","c":"بَعْدَ","d":"baʿda","e":"after"},{"b":"8.8","h":"15.43","c":"مَوْتِهَا","d":"mawtihā","e":"its death"},{"b":"10.4","h":"18.9","c":"وَكَذَلِكَ","d":"wakadhālika","e":"and thus"},{"b":"11.6","h":"20.96","c":"تُخْرَجُونَ","d":"tukh'rajūna","e":"you will be brought forth"}],"a":{"g":"He brings the living out of the dead and brings the dead out of the living and brings to life the earth after its lifelessness. And thus will you be brought out."}},"20":{"w":[{"b":"0.05","h":"0.62","c":"وَمِنْ","d":"wamin","e":"And among"},{"b":"0.65","h":"1.46","c":"ءَايَاتِهِ","d":"āyātihi","e":"His Signs"},{"b":"3.5","h":"5.35","c":"أَنْ","d":"an","e":"(is) that"},{"b":"3.7","h":"5.93","c":"خَلَقَكُمْ","d":"khalaqakum","e":"He created you"},{"b":"5.5","h":"8.52","c":"مِنْ","d":"min","e":"from"},{"b":"6.3","h":"9.43","c":"تُرَابٍ","d":"turābin","e":"dust"},{"b":"7.9","h":"11.69","c":"ثُمَّ","d":"thumma","e":"then"},{"b":"9.1","h":"13.39","c":"إِذَا","d":"idhā","e":"behold!"},{"b":"9.4","h":"15.44","c":"أَنْتُمْ","d":"antum","e":"You"},{"b":"13.1","h":"17.92","c":"بَشَرٌ","d":"basharun","e":"(are) human beings"},{"b":"14.5","h":"19.93","c":"تَنْتَشِرُونَ","d":"tantashirūna","e":"dispersing"}],"a":{"g":"And of His signs is that He created you from dust; then, suddenly you were human beings dispersing [throughout the earth]."}},"21":{"w":[{"b":"0.33","h":"0.4","c":"وَمِنْ","d":"wamin","e":"And among"},{"b":"0.94","h":"1.24","c":"ءَايَاتِهِ","d":"āyātihi","e":"His Signs"},{"b":"3.8","h":"5.16","c":"أَنْ","d":"an","e":"(is) that"},{"b":"4.1","h":"5.69","c":"خَلَقَ","d":"khalaqa","e":"He created"},{"b":"4.8","h":"6.92","c":"لَكُمْ","d":"lakum","e":"for you"},{"b":"6.1","h":"8.56","c":"مِنْ","d":"min","e":"from"},{"b":"6.4","h":"9.12","c":"أَنْفُسِكُمْ","d":"anfusikum","e":"yourselves"},{"b":"8.4","h":"11.7","c":"أَزْوَاجًا","d":"azwājan","e":"mates"},{"b":"9.2","h":"13.53","c":"لِتَسْكُنُوا","d":"litaskunū","e":"that you may find tranquility"},{"b":"12.4","h":"16.69","c":"إِلَيْهَا","d":"ilayhā","e":"in them"},{"b":"13.4","h":"18.52","c":"وَجَعَلَ","d":"wajaʿala","e":"and He placed"},{"b":"14.2","h":"19.91","c":"بَيْنَكُمْ","d":"baynakum","e":"between you"},{"b":"15.8","h":"22.12","c":"مَوَدَّةً","d":"mawaddatan","e":"love"},{"b":"16.9","h":"24.95","c":"وَرَحْمَةً","d":"waraḥmatan","e":"and mercy"},{"b":"19.5","h":"28.4","c":"إِنَّ","d":"inna","e":"Indeed"},{"b":"20.6","h":"29.8","c":"فِي","d":"fī","e":"in"},{"b":"21.1","h":"30.66","c":"ذَلِكَ","d":"dhālika","e":"that"},{"b":"22.0","h":"32.22","c":"لَءَايَاتٍ","d":"laāyātin","e":"surely (are) Signs"},{"b":"23.2","h":"34.59","c":"لِقَوْمٍ","d":"liqawmin","e":"for a people"},{"b":"25.2","h":"37.21","c":"يَتَفَكَّرُونَ","d":"yatafakkarūna","e":"who reflect"}],"a":{"g":"And of His signs is that He created for you from yourselves mates that you may find tranquillity in them; and He placed between you affection and mercy. Indeed in that are signs for a people who give thought."}},"22":{"w":[{"b":"0.35","h":"0.4","c":"وَمِنْ","d":"wamin","e":"And among"},{"b":"0.97","h":"1.18","c":"ءَايَاتِهِ","d":"āyātihi","e":"His Signs"},{"b":"2.4","h":"3.99","c":"خَلْقُ","d":"khalqu","e":"(is the) creation"},{"b":"3.1","h":"5.21","c":"السَّمَاوَاتِ","d":"l-samāwāti","e":"(of) the heavens"},{"b":"4.7","h":"8.11","c":"وَالْأَرْضِ","d":"wal-arḍi","e":"and the earth"},{"b":"5.7","h":"9.91","c":"وَاخْتِلَافُ","d":"wa-ikh'tilāfu","e":"and the diversity"},{"b":"6.9","h":"12.13","c":"أَلْسِنَتِكُمْ","d":"alsinatikum","e":"(of) your languages"},{"b":"8.4","h":"14.63","c":"وَأَلْوَانِكُمْ","d":"wa-alwānikum","e":"and your colors"},{"b":"10.6","h":"20.15","c":"إِنَّ","d":"inna","e":"Indeed"},{"b":"11.7","h":"21.66","c":"فِي","d":"fī","e":"in"},{"b":"12.2","h":"22.5","c":"ذَلِكَ","d":"dhālika","e":"that"},{"b":"13.1","h":"24.11","c":"لَءَايَاتٍ","d":"laāyātin","e":"surely (are) Signs"},{"b":"14.4","h":"26.57","c":"لِلْعَالِمِينَ","d":"lil'ʿālimīna","e":"for those of knowledge"}],"a":{"g":"And of His signs is the creation of the heavens and the earth and the diversity of your languages and your colors. Indeed in that are signs for those of knowledge."}},"23":{"w":[{"b":"0.18","h":"0.24","c":"وَمِنْ","d":"wamin","e":"And among"},{"b":"0.74","h":"1.03","c":"ءَايَاتِهِ","d":"āyātihi","e":"His Signs"},{"b":"2.3","h":"3.88","c":"مَنَامُكُمْ","d":"manāmukum","e":"(is) your sleep"},{"b":"4.0","h":"6.53","c":"بِاللَّيْلِ","d":"bi-al-layli","e":"by night"},{"b":"5.1","h":"8.44","c":"وَالنَّهَارِ","d":"wal-nahāri","e":"and the day"},{"b":"6.8","h":"10.99","c":"وَابْتِغَاؤُكُمْ","d":"wa-ib'tighāukum","e":"[and] your seeking"},{"b":"10.8","h":"15.6","c":"مِنْ","d":"min","e":"of"},{"b":"11.8","h":"16.67","c":"فَضْلِهِ","d":"faḍlihi","e":"His Bounty"},{"b":"13.2","h":"20.45","c":"إِنَّ","d":"inna","e":"Indeed"},{"b":"14.5","h":"22.13","c":"فِي","d":"fī","e":"in"},{"b":"15.0","h":"22.97","c":"ذَلِكَ","d":"dhālika","e":"that"},{"b":"15.9","h":"24.58","c":"لَءَايَاتٍ","d":"laāyātin","e":"surely (are) Signs"},{"b":"17.2","h":"27.16","c":"لِقَوْمٍ","d":"liqawmin","e":"for a people"},{"b":"19.4","h":"30.19","c":"يَسْمَعُونَ","d":"yasmaʿūna","e":"who listen"}],"a":{"g":"And of His signs is your sleep by night and day and your seeking of His bounty. Indeed in that are signs for a people who listen."}},"24":{"w":[{"b":"0.29","h":"0.55","c":"وَمِنْ","d":"wamin","e":"And among"},{"b":"0.89","h":"1.31","c":"ءَايَاتِهِ","d":"āyātihi","e":"His Signs"},{"b":"2.3","h":"4.19","c":"يُرِيكُمُ","d":"yurīkumu","e":"He shows you"},{"b":"3.5","h":"5.98","c":"الْبَرْقَ","d":"l-barqa","e":"the lightning"},{"b":"4.2","h":"7.4","c":"خَوْفًا","d":"khawfan","e":"(causing) fear"},{"b":"5","h":"8.65","c":"وَطَمَعًا","d":"waṭamaʿan","e":"and hope"},{"b":"6.6","h":"10.88","c":"وَيُنَزِّلُ","d":"wayunazzilu","e":"and He sends down"},{"b":"8.6","h":"13.89","c":"مِنَ","d":"mina","e":"from"},{"b":"9.0","h":"14.57","c":"السَّمَاءِ","d":"l-samāi","e":"the sky"},{"b":"11.5","h":"17.27","c":"مَاءً","d":"māan","e":"water"},{"b":"14.4","h":"20.15","c":"فَيُحْيِي","d":"fayuḥ'yī","e":"and gives life"},{"b":"15.","h":"22.06","c":"بِهِ","d":"bihi","e":"therewith"},{"b":"16.0","h":"22.75","c":"الْأَرْضَ","d":"l-arḍa","e":"(to) the earth"},{"b":"16.8","h":"24.23","c":"بَعْدَ","d":"baʿda","e":"after"},{"b":"17.5","h":"25.39","c":"مَوْتِهَا","d":"mawtihā","e":"its death"},{"b":"19.2","h":"29.8","c":"إِنَّ","d":"inna","e":"Indeed"},{"b":"20.6","h":"31.26","c":"فِي","d":"fī","e":"in"},{"b":"21.1","h":"32.08","c":"ذَلِكَ","d":"dhālika","e":"that"},{"b":"22.0","h":"33.6","c":"لَءَايَاتٍ","d":"laāyātin","e":"surely (are) Signs"},{"b":"23.4","h":"36.08","c":"لِقَوْمٍ","d":"liqawmin","e":"for a people"},{"b":"25.6","h":"38.76","c":"يَعْقِلُونَ","d":"yaʿqilūna","e":"who use intellect"}],"a":{"g":"And of His signs is [that] He shows you the lightning [causing] fear and aspiration, and He sends down rain from the sky by which He brings to life the earth after its lifelessness. Indeed in that are signs for a people who use reason."}},"25":{"w":[{"b":"0.26","h":"0.51","c":"وَمِنْ","d":"wamin","e":"And among"},{"b":"0.86","h":"1.3","c":"ءَايَاتِهِ","d":"āyātihi","e":"His Signs"},{"b":"3.7","h":"4.82","c":"أَنْ","d":"an","e":"(is) that"},{"b":"4.8","h":"5.82","c":"تَقُومَ","d":"taqūma","e":"stands"},{"b":"5.7","h":"7.46","c":"السَّمَاءُ","d":"l-samāu","e":"the heavens"},{"b":"8.3","h":"10.46","c":"وَالْأَرْضُ","d":"wal-arḍu","e":"and the earth"},{"b":"9.3","h":"12.39","c":"بِأَمْرِهِ","d":"bi-amrihi","e":"by His Command"},{"b":"10.8","h":"17","c":"ثُمَّ","d":"thumma","e":"Then"},{"b":"12.0","h":"18.43","c":"إِذَا","d":"idhā","e":"when"},{"b":"12.7","h":"19.7","c":"دَعَاكُمْ","d":"daʿākum","e":"He calls you"},{"b":"13.8","h":"21.67","c":"دَعْوَةً","d":"daʿwatan","e":"(with) a call"},{"b":"15.5","h":"23.63","c":"مِنَ","d":"mina","e":"from"},{"b":"15.8","h":"24.89","c":"الْأَرْضِ","d":"l-arḍi","e":"the earth"},{"b":"16.6","h":"26.4","c":"إِذَا","d":"idhā","e":"behold!"},{"b":"18.2","h":"28.57","c":"أَنْتُمْ","d":"antum","e":"You"},{"b":"20.","h":"30.67","c":"تَخْرُجُونَ","d":"takhrujūna","e":"will come forth"}],"a":{"g":"And of His signs is that the heaven and earth remain by His command. Then when He calls you with a [single] call from the earth, immediately you will come forth."}},"26":{"w":[{"b":"0.2","h":"0.45","c":"وَلَهُ","d":"walahu","e":"And to Him (belongs)"},{"b":"1.0","h":"1.9","c":"مَنْ","d":"man","e":"whoever"},{"b":"2.1","h":"2.92","c":"فِي","d":"fī","e":"(is) in"},{"b":"2.3","h":"3.31","c":"السَّمَاوَاتِ","d":"l-samāwāti","e":"the heavens"},{"b":"3.9","h":"6.37","c":"وَالْأَرْضِ","d":"wal-arḍi","e":"and the earth"},{"b":"5.3","h":"9.95","c":"كُلٌّ","d":"kullun","e":"All"},{"b":"5.9","h":"11.24","c":"لَهُ","d":"lahu","e":"to Him"},{"b":"6.7","h":"12.15","c":"قَانِتُونَ","d":"qānitūna","e":"(are) obedient"}],"a":{"g":"And to Him belongs whoever is in the heavens and earth. All are to Him devoutly obedient."}},"27":{"w":[{"b":"0.3","h":"0.7","c":"وَهُوَ","d":"wahuwa","e":"And He"},{"b":"0.99","h":"1.54","c":"الَّذِي","d":"alladhī","e":"(is) the One Who"},{"b":"1.8","h":"2.88","c":"يَبْدَؤُا","d":"yabda-u","e":"originates"},{"b":"2.6","h":"4.2","c":"الْخَلْقَ","d":"l-khalqa","e":"the creation"},{"b":"3.4","h":"5.57","c":"ثُمَّ","d":"thumma","e":"then"},{"b":"4.6","h":"6.98","c":"يُعِيدُهُ","d":"yuʿīduhu","e":"repeats it"},{"b":"6.0","h":"9.29","c":"وَهُوَ","d":"wahuwa","e":"and it"},{"b":"6.7","h":"10.33","c":"أَهْوَنُ","d":"ahwanu","e":"(is) easier"},{"b":"7.5","h":"11.64","c":"عَلَيْهِ","d":"ʿalayhi","e":"for Him"},{"b":"10.2","h":"16.85","c":"وَلَهُ","d":"walahu","e":"And for Him"},{"b":"10.9","h":"17.75","c":"الْمَثَلُ","d":"l-mathalu","e":"(is) the description"},{"b":"11.","h":"19.14","c":"الْأَعْلَى","d":"l-aʿlā","e":"the highest"},{"b":"12.","h":"20.98","c":"فِي","d":"fī","e":"in"},{"b":"13.1","h":"21.36","c":"السَّمَاوَاتِ","d":"l-samāwāti","e":"the heavens"},{"b":"14.7","h":"24.07","c":"وَالْأَرْضِ","d":"wal-arḍi","e":"and the earth"},{"b":"16.1","h":"27.45","c":"وَهُوَ","d":"wahuwa","e":"And He"},{"b":"16.8","h":"28.36","c":"الْعَزِيزُ","d":"l-ʿazīzu","e":"(is) the All-Mighty"},{"b":"17.9","h":"30.28","c":"الْحَكِيمُ","d":"l-ḥakīmu","e":"the All-Wise"}],"a":{"g":"And it is He who begins creation; then He repeats it, and that is [even] easier for Him. To Him belongs the highest attribute in the heavens and earth. And He is the Exalted in Might, the Wise."}},"28":{"w":[{"b":"0.17","h":"0.8","c":"ضَرَبَ","d":"ḍaraba","e":"He sets forth"},{"b":"0.84","h":"1.76","c":"لَكُمْ","d":"lakum","e":"to you"},{"b":"2.0","h":"3.19","c":"مَثَلًا","d":"mathalan","e":"an example"},{"b":"2.4","h":"4.29","c":"مِنْ","d":"min","e":"from"},{"b":"3.9","h":"5.85","c":"أَنْفُسِكُمْ","d":"anfusikum","e":"yourselves"},{"b":"6.7","h":"11.4","c":"هَلْ","d":"hal","e":"Is"},{"b":"7.1","h":"12.03","c":"لَكُمْ","d":"lakum","e":"for you"},{"b":"8.5","h":"13.38","c":"مِنْ","d":"min","e":"among"},{"b":"8.6","h":"14.64","c":"مَا","d":"mā","e":"what"},{"b":"9.9","h":"15.3","c":"مَلَكَتْ","d":"malakat","e":"posses"},{"b":"10.8","h":"16.76","c":"أَيْمَانُكُمْ","d":"aymānukum","e":"your right hands"},{"b":"12.9","h":"19.78","c":"مِنْ","d":"min","e":"any"},{"b":"14.0","h":"20.72","c":"شُرَكَاءَ","d":"shurakāa","e":"partners"},{"b":"16.5","h":"23.34","c":"فِي","d":"fī","e":"in"},{"b":"17.0","h":"24.15","c":"مَا","d":"mā","e":"what"},{"b":"17.3","h":"24.99","c":"رَزَقْنَاكُمْ","d":"razaqnākum","e":"We have provided you"},{"b":"18.8","h":"27.59","c":"فَأَنْتُمْ","d":"fa-antum","e":"so you"},{"b":"20.7","h":"29.94","c":"فِيهِ","d":"fīhi","e":"in it"},{"b":"26.8","h":"31.19","c":"سَوَاءٌ","d":"sawāon","e":"(are) equal"},{"b":"29.6","h":"42.14","c":"تَخَافُونَهُمْ","d":"takhāfūnahum","e":"you fear them"},{"b":"31.3","h":"45.15","c":"كَخِيفَتِكُمْ","d":"kakhīfatikum","e":"as you fear"},{"b":"32.9","h":"47.83","c":"أَنْفُسَكُمْ","d":"anfusakum","e":"yourselves"},{"b":"35.4","h":"52.85","c":"كَذَلِكَ","d":"kadhālika","e":"Thus"},{"b":"36.4","h":"54.42","c":"نُفَصِّلُ","d":"nufaṣṣilu","e":"We explain"},{"b":"37.5","h":"56.23","c":"الْءَايَاتِ","d":"l-āyāti","e":"the Verses"},{"b":"38.8","h":"58.42","c":"لِقَوْمٍ","d":"liqawmin","e":"for a people"},{"b":"40.6","h":"60.94","c":"يَعْقِلُونَ","d":"yaʿqilūna","e":"(who) use reason"}],"a":{"g":"He presents to you an example from yourselves. Do you have among those whom your right hands possess any partners in what We have provided for you so that you are equal therein [and] would fear them as your fear of one another [within a partnership]? Thus do We detail the verses for a people who use reason."}},"29":{"w":[{"b":"0.45","h":"0.4","c":"بَلِ","d":"bali","e":"Nay"},{"b":"0.99","h":"0.87","c":"اتَّبَعَ","d":"ittabaʿa","e":"follow"},{"b":"1.6","h":"2.28","c":"الَّذِينَ","d":"alladhīna","e":"those who"},{"b":"2.7","h":"3.9","c":"ظَلَمُوا","d":"ẓalamū","e":"do wrong"},{"b":"5.0","h":"6.29","c":"أَهْوَاءَهُمْ","d":"ahwāahum","e":"their desires"},{"b":"8.9","h":"10.06","c":"بِغَيْرِ","d":"bighayri","e":"without"},{"b":"9.7","h":"11.61","c":"عِلْمٍ","d":"ʿil'min","e":"knowledge"},{"b":"10.8","h":"14.35","c":"فَمَنْ","d":"faman","e":"Then who"},{"b":"12.2","h":"15.76","c":"يَهْدِي","d":"yahdī","e":"(can) guide"},{"b":"12.9","h":"17.19","c":"مَنْ","d":"man","e":"(one) whom"},{"b":"13.2","h":"17.86","c":"أَضَلَّ","d":"aḍalla","e":"Allah has let go astray"},{"b":"14.0","h":"19.29","c":"اللَّهُ","d":"l-lahu","e":"Allah has let go astray"},{"b":"17.3","h":"20.81","c":"وَمَا","d":"wamā","e":"And not"},{"b":"18.0","h":"22.15","c":"لَهُمْ","d":"lahum","e":"for them"},{"b":"18.4","h":"23.59","c":"مِنْ","d":"min","e":"any"},{"b":"20.4","h":"24.02","c":"نَاصِرِينَ","d":"nāṣirīna","e":"helpers"}],"a":{"g":"But those who wrong follow their [own] desires without knowledge. Then who can guide one whom Allah has sent astray? And for them there are no helpers."}},"30":{"w":[{"b":"0.13","h":"0.8","c":"فَأَقِمْ","d":"fa-aqim","e":"So set"},{"b":"0.92","h":"1.91","c":"وَجْهَكَ","d":"wajhaka","e":"your face"},{"b":"1.8","h":"3.52","c":"لِلدِّينِ","d":"lilddīni","e":"to the religion"},{"b":"2.8","h":"5.17","c":"حَنِيفًا","d":"ḥanīfan","e":"upright"},{"b":"4.4","h":"9.05","c":"فِطْرَتَ","d":"fiṭ'rata","e":"Nature"},{"b":"5.3","h":"10.24","c":"اللَّهِ","d":"l-lahi","e":"(made by) Allah"},{"b":"6.2","h":"11.66","c":"الَّتِي","d":"allatī","e":"(upon) which"},{"b":"7.0","h":"13.09","c":"فَطَرَ","d":"faṭara","e":"He has created"},{"b":"7.8","h":"14.27","c":"النَّاسَ","d":"l-nāsa","e":"mankind"},{"b":"9.2","h":"15.97","c":"عَلَيْهَا","d":"ʿalayhā","e":"[on it]"},{"b":"10.8","h":"19.6","c":"لَا","d":"lā","e":"No"},{"b":"11.1","h":"20.24","c":"تَبْدِيلَ","d":"tabdīla","e":"change"},{"b":"12.3","h":"22.14","c":"لِخَلْقِ","d":"likhalqi","e":"(should there be) in the creation"},{"b":"13.2","h":"23.61","c":"اللَّهِ","d":"l-lahi","e":"(of) Allah"},{"b":"15.7","h":"27.6","c":"ذَلِكَ","d":"dhālika","e":"That"},{"b":"16.6","h":"29.1","c":"الدِّينُ","d":"l-dīnu","e":"(is) the religion"},{"b":"17.4","h":"30.68","c":"الْقَيِّمُ","d":"l-qayimu","e":"the correct"},{"b":"18.5","h":"32.57","c":"وَلَكِنَّ","d":"walākinna","e":"but"},{"b":"20.","h":"35.15","c":"أَكْثَرَ","d":"akthara","e":"most"},{"b":"21.4","h":"36.64","c":"النَّاسِ","d":"l-nāsi","e":"men"},{"b":"22.9","h":"38.43","c":"لَا","d":"lā","e":"(do) not"},{"b":"23.3","h":"39.25","c":"يَعْلَمُونَ","d":"yaʿlamūna","e":"know"}],"a":{"g":"So direct your face toward the religion, inclining to truth. [Adhere to] the fitrah of Allah upon which He has created [all] people. No change should there be in the creation of Allah. That is the correct religion, but most of the people do not know."}},"31":{"w":[{"b":"0.21","h":"0.65","c":"مُنِيبِينَ","d":"munībīna","e":"Turning"},{"b":"1.4","h":"2.53","c":"إِلَيْهِ","d":"ilayhi","e":"to Him"},{"b":"2.3","h":"3.88","c":"وَاتَّقُوهُ","d":"wa-ittaqūhu","e":"and fear Him"},{"b":"3.6","h":"5.95","c":"وَأَقِيمُوا","d":"wa-aqīmū","e":"and establish"},{"b":"4.6","h":"7.81","c":"الصَّلَوةَ","d":"l-ṣalata","e":"the prayer"},{"b":"5.7","h":"9.53","c":"وَلَا","d":"walā","e":"and (do) not"},{"b":"6.3","h":"10.49","c":"تَكُونُوا","d":"takūnū","e":"be"},{"b":"7.5","h":"12.41","c":"مِنَ","d":"mina","e":"of"},{"b":"7.9","h":"13","c":"الْمُشْرِكِينَ","d":"l-mush'rikīna","e":"the polytheists"}],"a":{"g":"[Adhere to it], turning in repentance to Him, and fear Him and establish prayer and do not be of those who associate others with Allah"}},"32":{"w":[{"b":"0.24","h":"0.16","c":"مِنَ","d":"mina","e":"Of"},{"b":"0.54","h":"0.61","c":"الَّذِينَ","d":"alladhīna","e":"those who"},{"b":"1.6","h":"2.32","c":"فَرَّقُوا","d":"farraqū","e":"divide"},{"b":"2.7","h":"4.18","c":"دِينَهُمْ","d":"dīnahum","e":"their religion"},{"b":"3.8","h":"5.92","c":"وَكَانُوا","d":"wakānū","e":"and become"},{"b":"4.8","h":"7.84","c":"شِيَعًا","d":"shiyaʿan","e":"sects"},{"b":"5.9","h":"11.05","c":"كُلُّ","d":"kullu","e":"each"},{"b":"6.8","h":"11.9","c":"حِزْبٍ","d":"ḥiz'bin","e":"party"},{"b":"8.7","h":"13.9","c":"بِمَا","d":"bimā","e":"in what"},{"b":"9.3","h":"15.05","c":"لَدَيْهِمْ","d":"ladayhim","e":"they have"},{"b":"10.","h":"16.92","c":"فَرِحُونَ","d":"fariḥūna","e":"rejoicing"}],"a":{"g":"[Or] of those who have divided their religion and become sects, every faction rejoicing in what it has."}},"33":{"w":[{"b":"0.18","h":"0.7","c":"وَإِذَا","d":"wa-idhā","e":"And when"},{"b":"1.0","h":"1.97","c":"مَسَّ","d":"massa","e":"touches"},{"b":"1.6","h":"3.07","c":"النَّاسَ","d":"l-nāsa","e":"men"},{"b":"3.1","h":"4.89","c":"ضُرٌّ","d":"ḍurrun","e":"hardship"},{"b":"4.6","h":"6.83","c":"دَعَوْا","d":"daʿaw","e":"they call"},{"b":"5.3","h":"7.98","c":"رَبَّهُمْ","d":"rabbahum","e":"their Lord"},{"b":"7.1","h":"10.63","c":"مُنِيبِينَ","d":"munībīna","e":"turning"},{"b":"8.3","h":"12.4","c":"إِلَيْهِ","d":"ilayhi","e":"to Him"},{"b":"15.7","h":"13.93","c":"ثُمَّ","d":"thumma","e":"Then"},{"b":"17.1","h":"15.48","c":"إِذَا","d":"idhā","e":"when"},{"b":"19.0","h":"15.94","c":"أَذَاقَهُمْ","d":"adhāqahum","e":"He causes them to taste"},{"b":"21.1","h":"19.93","c":"مِنْهُ","d":"min'hu","e":"from Him"},{"b":"21.6","h":"20.93","c":"رَحْمَةً","d":"raḥmatan","e":"Mercy"},{"b":"22.","h":"22.75","c":"إِذَا","d":"idhā","e":"behold!"},{"b":"23.3","h":"23.8","c":"فَرِيقٌ","d":"farīqun","e":"A party"},{"b":"25.1","h":"26.34","c":"مِنْهُمْ","d":"min'hum","e":"of them"},{"b":"26.4","h":"44.61","c":"بِرَبِّهِمْ","d":"birabbihim","e":"with their Lord"},{"b":"27.7","h":"46.92","c":"يُشْرِكُونَ","d":"yush'rikūna","e":"associate partners"}],"a":{"g":"And when adversity touches the people, they call upon their Lord, turning in repentance to Him. Then when He lets them taste mercy from Him, at once a party of them associate others with their Lord,"}},"34":{"w":[{"b":"0.27","h":"0.6","c":"لِيَكْفُرُوا","d":"liyakfurū","e":"So as to deny"},{"b":"1.5","h":"2.75","c":"بِمَا","d":"bimā","e":"[in] what"},{"b":"3.5","h":"4.8","c":"ءَاتَيْنَاهُمْ","d":"ātaynāhum","e":"We have granted them"},{"b":"5.7","h":"7.86","c":"فَتَمَتَّعُوا","d":"fatamattaʿū","e":"Then enjoy"},{"b":"7.1","h":"10.63","c":"فَسَوْفَ","d":"fasawfa","e":"but soon"},{"b":"8.0","h":"12.16","c":"تَعْلَمُونَ","d":"taʿlamūna","e":"you will know"}],"a":{"g":"So that they will deny what We have granted them. Then enjoy yourselves, for you are going to know."}},"35":{"w":[{"b":"0.11","h":"0.5","c":"أَمْ","d":"am","e":"Or"},{"b":"0.49","h":"1.04","c":"أَنْزَلْنَا","d":"anzalnā","e":"have We sent"},{"b":"2.5","h":"3.52","c":"عَلَيْهِمْ","d":"ʿalayhim","e":"to them"},{"b":"3.5","h":"5.42","c":"سُلْطَانًا","d":"sul'ṭānan","e":"an authority"},{"b":"5.3","h":"7.31","c":"فَهُوَ","d":"fahuwa","e":"and it"},{"b":"6.0","h":"9.09","c":"يَتَكَلَّمُ","d":"yatakallamu","e":"speaks"},{"b":"7.3","h":"11.35","c":"بِمَا","d":"bimā","e":"of what"},{"b":"7.9","h":"12.4","c":"كَانُوا","d":"kānū","e":"they were"},{"b":"8.8","h":"14.07","c":"بِهِ","d":"bihi","e":"with Him"},{"b":"9.6","h":"15.27","c":"يُشْرِكُونَ","d":"yush'rikūna","e":"associating"}],"a":{"g":"Or have We sent down to them an authority, and it speaks of what they were associating with Him?"}},"36":{"w":[{"b":"0.22","h":"0.16","c":"وَإِذَا","d":"wa-idhā","e":"And when"},{"b":"2.2","h":"2.43","c":"أَذَقْنَا","d":"adhaqnā","e":"We cause men to taste"},{"b":"3.1","h":"3.9","c":"النَّاسَ","d":"l-nāsa","e":"We cause men to taste"},{"b":"4.9","h":"5.85","c":"رَحْمَةً","d":"raḥmatan","e":"mercy"},{"b":"7.2","h":"8.36","c":"فَرِحُوا","d":"fariḥū","e":"they rejoice"},{"b":"8.1","h":"10.12","c":"بِهَا","d":"bihā","e":"therein"},{"b":"9.4","h":"13.12","c":"وَإِنْ","d":"wa-in","e":"But if"},{"b":"10.6","h":"14.48","c":"تُصِبْهُمْ","d":"tuṣib'hum","e":"afflicts them"},{"b":"11.6","h":"16.16","c":"سَيِّئَةٌ","d":"sayyi-atun","e":"an evil"},{"b":"13.6","h":"18.94","c":"بِمَا","d":"bimā","e":"for what"},{"b":"14.2","h":"20","c":"قَدَّمَتْ","d":"qaddamat","e":"have sent forth"},{"b":"15.","h":"21.9","c":"أَيْدِيهِمْ","d":"aydīhim","e":"their hands"},{"b":"16.","h":"24.06","c":"إِذَا","d":"idhā","e":"behold"},{"b":"17.1","h":"25.1","c":"هُمْ","d":"hum","e":"They"},{"b":"17.6","h":"25.8","c":"يَقْنَطُونَ","d":"yaqnaṭūna","e":"despair"}],"a":{"g":"And when We let the people taste mercy, they rejoice therein, but if evil afflicts them for what their hands have put forth, immediately they despair."}},"37":{"w":[{"b":"0.22","h":"0.6","c":"أَوَلَمْ","d":"awalam","e":"Do not"},{"b":"0.98","h":"1.7","c":"يَرَوْا","d":"yaraw","e":"they see"},{"b":"1.6","h":"2.88","c":"أَنَّ","d":"anna","e":"that"},{"b":"3.1","h":"4.24","c":"اللَّهَ","d":"l-laha","e":"Allah"},{"b":"4","h":"5.63","c":"يَبْسُطُ","d":"yabsuṭu","e":"extends"},{"b":"4.8","h":"7.01","c":"الرِّزْقَ","d":"l-riz'qa","e":"the provision"},{"b":"5.6","h":"8.5","c":"لِمَنْ","d":"liman","e":"for whom"},{"b":"7.2","h":"10.07","c":"يَشَاءُ","d":"yashāu","e":"He wills"},{"b":"9.7","h":"12.53","c":"وَيَقْدِرُ","d":"wayaqdiru","e":"and straitens (it)"},{"b":"11.1","h":"15.85","c":"إِنَّ","d":"inna","e":"Indeed"},{"b":"12.7","h":"17.04","c":"فِي","d":"fī","e":"in"},{"b":"13.2","h":"17.93","c":"ذَلِكَ","d":"dhālika","e":"that"},{"b":"14.1","h":"19.48","c":"لَءَايَاتٍ","d":"laāyātin","e":"surely (are) Signs"},{"b":"15.5","h":"21.9","c":"لِقَوْمٍ","d":"liqawmin","e":"for a people"},{"b":"17.6","h":"24.53","c":"يُؤْمِنُونَ","d":"yu'minūna","e":"who believe"}],"a":{"g":"Do they not see that Allah extends provision for whom He wills and restricts [it]? Indeed, in that are signs for a people who believe."}},"38":{"w":[{"b":"0.24","h":"0.55","c":"فَءَاتِ","d":"faāti","e":"So give"},{"b":"1.1","h":"1.82","c":"ذَا","d":"dhā","e":"the relative"},{"b":"1.2","h":"2.18","c":"الْقُرْبَى","d":"l-qur'bā","e":"the relative"},{"b":"2.3","h":"3.98","c":"حَقَّهُ","d":"ḥaqqahu","e":"his right"},{"b":"3.4","h":"5.87","c":"وَالْمِسْكِينَ","d":"wal-mis'kīna","e":"and the poor"},{"b":"4.9","h":"8.46","c":"وَابْنَ","d":"wa-ib'na","e":"and the wayfarer"},{"b":"5.5","h":"9.52","c":"السَّبِيلِ","d":"l-sabīli","e":"and the wayfarer"},{"b":"9.1","h":"13.8","c":"ذَلِكَ","d":"dhālika","e":"That"},{"b":"9.9","h":"15.25","c":"خَيْرٌ","d":"khayrun","e":"(is) best"},{"b":"10.8","h":"16.51","c":"لِلَّذِينَ","d":"lilladhīna","e":"for those who"},{"b":"12.0","h":"18.95","c":"يُرِيدُونَ","d":"yurīdūna","e":"desire"},{"b":"13.3","h":"21.27","c":"وَجْهَ","d":"wajha","e":"(the) Countenance"},{"b":"14.0","h":"22.41","c":"اللَّهِ","d":"l-lahi","e":"(of) Allah"},{"b":"17.0","h":"26.61","c":"وَأُولَئِكَ","d":"wa-ulāika","e":"And those"},{"b":"20.1","h":"29.76","c":"هُمُ","d":"humu","e":"they"},{"b":"20.5","h":"30.63","c":"الْمُفْلِحُونَ","d":"l-muf'liḥūna","e":"(are) the successful ones"}],"a":{"g":"So give the relative his right, as well as the needy and the traveler. That is best for those who desire the countenance of Allah, and it is they who will be the successful."}},"39":{"w":[{"b":"0.32","h":"0.9","c":"وَمَا","d":"wamā","e":"And what"},{"b":"2.6","h":"2.54","c":"ءَاتَيْتُمْ","d":"ātaytum","e":"you give"},{"b":"4.7","h":"5.46","c":"مِنْ","d":"min","e":"for"},{"b":"4.8","h":"5.7","c":"رِبًا","d":"riban","e":"usury"},{"b":"5.4","h":"6.81","c":"لِيَرْبُوَا","d":"liyarbuwā","e":"to increase"},{"b":"6.7","h":"9.03","c":"فِي","d":"fī","e":"in"},{"b":"8.6","h":"10.73","c":"أَمْوَالِ","d":"amwāli","e":"(the) wealth"},{"b":"9.6","h":"12.73","c":"النَّاسِ","d":"l-nāsi","e":"(of) people"},{"b":"11.3","h":"14.55","c":"فَلَا","d":"falā","e":"not"},{"b":"11.9","h":"15.82","c":"يَرْبُوا","d":"yarbū","e":"(will) increase"},{"b":"12.8","h":"17.75","c":"عِنْدَ","d":"ʿinda","e":"with"},{"b":"14.3","h":"19.04","c":"اللَّهِ","d":"l-lahi","e":"Allah"},{"b":"17.0","h":"23.95","c":"وَمَا","d":"wamā","e":"But what"},{"b":"19.0","h":"25.96","c":"ءَاتَيْتُمْ","d":"ātaytum","e":"you give"},{"b":"20.8","h":"28.79","c":"مِنْ","d":"min","e":"of"},{"b":"21.9","h":"29.76","c":"زَكَوةٍ","d":"zakatin","e":"zakah"},{"b":"23.7","h":"32.23","c":"تُرِيدُونَ","d":"turīdūna","e":"desiring"},{"b":"25.0","h":"34.61","c":"وَجْهَ","d":"wajha","e":"(the) Countenance"},{"b":"25.6","h":"35.76","c":"اللَّهِ","d":"l-lahi","e":"(of) Allah"},{"b":"26.","h":"37.37","c":"فَأُولَئِكَ","d":"fa-ulāika","e":"then those"},{"b":"29.","h":"41.01","c":"هُمُ","d":"humu","e":"[they]"},{"b":"30.0","h":"41.89","c":"الْمُضْعِفُونَ","d":"l-muḍ'ʿifūna","e":"(will) get manifold"}],"a":{"g":"And whatever you give for interest to increase within the wealth of people will not increase with Allah. But what you give in zakah, desiring the countenance of Allah - those are the multipliers."}},"40":{"w":[{"b":"0.23","h":"0.59","c":"اللَّهُ","d":"al-lahu","e":"Allah"},{"b":"1.2","h":"2.25","c":"الَّذِي","d":"alladhī","e":"(is) the One Who"},{"b":"2.0","h":"3.72","c":"خَلَقَكُمْ","d":"khalaqakum","e":"created you"},{"b":"3.1","h":"5.67","c":"ثُمَّ","d":"thumma","e":"then"},{"b":"4.3","h":"7.04","c":"رَزَقَكُمْ","d":"razaqakum","e":"He provided (for) you"},{"b":"5.4","h":"9.31","c":"ثُمَّ","d":"thumma","e":"then"},{"b":"6.7","h":"10.8","c":"يُمِيتُكُمْ","d":"yumītukum","e":"He will cause you to die"},{"b":"8","h":"13.32","c":"ثُمَّ","d":"thumma","e":"then"},{"b":"9.3","h":"14.9","c":"يُحْيِيكُمْ","d":"yuḥ'yīkum","e":"He will give you life"},{"b":"11.2","h":"19.35","c":"هَلْ","d":"hal","e":"Is (there)"},{"b":"11.6","h":"20.05","c":"مِنْ","d":"min","e":"any"},{"b":"12.7","h":"21.34","c":"شُرَكَائِكُمْ","d":"shurakāikum","e":"(of) your partners"},{"b":"16.4","h":"26.14","c":"مَنْ","d":"man","e":"who"},{"b":"17.6","h":"27.2","c":"يَفْعَلُ","d":"yafʿalu","e":"does"},{"b":"18.4","h":"28.66","c":"مِنْ","d":"min","e":"of"},{"b":"19.6","h":"29.72","c":"ذَلِكُمْ","d":"dhālikum","e":"that"},{"b":"21.","h":"32.21","c":"مِنْ","d":"min","e":"any"},{"b":"22.","h":"33.67","c":"شَيْءٍ","d":"shayin","e":"thing"},{"b":"25.3","h":"37.85","c":"سُبْحَانَهُ","d":"sub'ḥānahu","e":"Glory be to Him"},{"b":"26.7","h":"40.36","c":"وَتَعَالَى","d":"wataʿālā","e":"and exalted is He"},{"b":"28.2","h":"42.53","c":"عَمَّا","d":"ʿammā","e":"above what"},{"b":"29.7","h":"44.96","c":"يُشْرِكُونَ","d":"yush'rikūna","e":"they associate"}],"a":{"g":"Allah is the one who created you, then provided for you, then will cause you to die, and then will give you life. Are there any of your \"partners\" who does anything of that? Exalted is He and high above what they associate with Him."}},"41":{"w":[{"b":"0.2","h":"0.2","c":"ظَهَرَ","d":"ẓahara","e":"Has appeared"},{"b":"0.95","h":"1.08","c":"الْفَسَادُ","d":"l-fasādu","e":"the corruption"},{"b":"2.0","h":"3.06","c":"فِي","d":"fī","e":"in"},{"b":"2.2","h":"3.53","c":"الْبَرِّ","d":"l-bari","e":"the land"},{"b":"3.1","h":"5.02","c":"وَالْبَحْرِ","d":"wal-baḥri","e":"and the sea"},{"b":"4.1","h":"6.85","c":"بِمَا","d":"bimā","e":"for what"},{"b":"4.7","h":"7.87","c":"كَسَبَتْ","d":"kasabat","e":"have earned"},{"b":"5.6","h":"9.57","c":"أَيْدِي","d":"aydī","e":"(the) hands"},{"b":"6.2","h":"10.69","c":"النَّاسِ","d":"l-nāsi","e":"(of) people"},{"b":"7.9","h":"12.59","c":"لِيُذِيقَهُمْ","d":"liyudhīqahum","e":"so that He may let them taste"},{"b":"11.8","h":"15.52","c":"بَعْضَ","d":"baʿḍa","e":"a part"},{"b":"12.4","h":"16.64","c":"الَّذِي","d":"alladhī","e":"(of) that which"},{"b":"13.2","h":"18.12","c":"عَمِلُوا","d":"ʿamilū","e":"they have done"},{"b":"14.","h":"19.87","c":"لَعَلَّهُمْ","d":"laʿallahum","e":"so that they may"},{"b":"15.4","h":"22.19","c":"يَرْجِعُونَ","d":"yarjiʿūna","e":"return"}],"a":{"g":"Corruption has appeared throughout the land and sea by [reason of] what the hands of people have earned so He may let them taste part of [the consequence of] what they have done that perhaps they will return [to righteousness]."}},"42":{"w":[{"b":"0.19","h":"0.85","c":"قُلْ","d":"qul","e":"Say"},{"b":"0.52","h":"1.32","c":"سِيرُوا","d":"sīrū","e":"Travel"},{"b":"1.4","h":"3.14","c":"فِي","d":"fī","e":"in"},{"b":"1.7","h":"3.57","c":"الْأَرْضِ","d":"l-arḍi","e":"the earth"},{"b":"2.5","h":"5.17","c":"فَانْظُرُوا","d":"fa-unẓurū","e":"and see"},{"b":"4.2","h":"7.82","c":"كَيْفَ","d":"kayfa","e":"how"},{"b":"4.9","h":"8.93","c":"كَانَ","d":"kāna","e":"was"},{"b":"5.5","h":"10.25","c":"عَاقِبَةُ","d":"ʿāqibatu","e":"(the) end"},{"b":"6.7","h":"12.22","c":"الَّذِينَ","d":"alladhīna","e":"(of) those who"},{"b":"7.8","h":"14.28","c":"مِنْ","d":"min","e":"(were) before"},{"b":"9.2","h":"15.64","c":"قَبْلُ","d":"qablu","e":"(were) before"},{"b":"10.1","h":"18.7","c":"كَانَ","d":"kāna","e":"Most of them were"},{"b":"10.7","h":"19.7","c":"أَكْثَرُهُمْ","d":"aktharuhum","e":"Most of them were"},{"b":"13.2","h":"23.14","c":"مُشْرِكِينَ","d":"mush'rikīna","e":"polytheists"}],"a":{"g":"Say, [O Muhammad], \"Travel through the land and observe how was the end of those before. Most of them were associators [of others with Allah]."}},"43":{"w":[{"b":"0.08","h":"0.55","c":"فَأَقِمْ","d":"fa-aqim","e":"So set"},{"b":"0.86","h":"1.22","c":"وَجْهَكَ","d":"wajhaka","e":"your face"},{"b":"1.7","h":"2.11","c":"لِلدِّينِ","d":"lilddīni","e":"to the religion"},{"b":"2.7","h":"3.17","c":"الْقَيِّمِ","d":"l-qayimi","e":"right"},{"b":"3.9","h":"4.38","c":"مِنْ","d":"min","e":"before"},{"b":"4.8","h":"5.3","c":"قَبْلِ","d":"qabli","e":"before"},{"b":"5.5","h":"6.06","c":"أَنْ","d":"an","e":"[that]"},{"b":"6.8","h":"7.24","c":"يَأْتِيَ","d":"yatiya","e":"comes"},{"b":"7.5","h":"7.91","c":"يَوْمٌ","d":"yawmun","e":"a Day"},{"b":"8.4","h":"8.71","c":"لَا","d":"lā","e":"not"},{"b":"8.9","h":"9.34","c":"مَرَدَّ","d":"maradda","e":"(can be) averted"},{"b":"9.7","h":"10.32","c":"لَهُ","d":"lahu","e":"[it]"},{"b":"10.","h":"11.02","c":"مِنَ","d":"mina","e":"from"},{"b":"10.","h":"11.52","c":"اللَّهِ","d":"l-lahi","e":"Allah"},{"b":"13.7","h":"16.1","c":"يَوْمَئِذٍ","d":"yawma-idhin","e":"That Day"},{"b":"16.0","h":"17.79","c":"يَصَّدَّعُونَ","d":"yaṣṣaddaʿūna","e":"they will be divided"}],"a":{"g":"So direct your face toward the correct religion before a Day comes from Allah of which there is no repelling. That Day, they will be divided."}},"44":{"w":[{"b":"0.13","h":"0.4","c":"مَنْ","d":"man","e":"Whoever"},{"b":"1.3","h":"1.32","c":"كَفَرَ","d":"kafara","e":"disbelieves"},{"b":"2.0","h":"2.12","c":"فَعَلَيْهِ","d":"faʿalayhi","e":"then against him"},{"b":"3.1","h":"3.3","c":"كُفْرُهُ","d":"kuf'ruhu","e":"(is) his disbelief"},{"b":"4.2","h":"5.85","c":"وَمَنْ","d":"waman","e":"And whoever"},{"b":"4.8","h":"6.25","c":"عَمِلَ","d":"ʿamila","e":"does"},{"b":"5.4","h":"7.01","c":"صَالِحًا","d":"ṣāliḥan","e":"righteousness"},{"b":"7.2","h":"8.88","c":"فَلِأَنْفُسِهِمْ","d":"fali-anfusihim","e":"then for themselves"},{"b":"9.6","h":"11.53","c":"يَمْهَدُونَ","d":"yamhadūna","e":"they are preparing"}],"a":{"g":"Whoever disbelieves - upon him is [the consequence of] his disbelief. And whoever does righteousness - they are for themselves preparing,"}},"45":{"w":[{"b":"0.16","h":"0.3","c":"لِيَجْزِيَ","d":"liyajziya","e":"That He may reward"},{"b":"1.1","h":"1.32","c":"الَّذِينَ","d":"alladhīna","e":"those who"},{"b":"2.3","h":"2.45","c":"ءَامَنُوا","d":"āmanū","e":"believe"},{"b":"3.3","h":"3.29","c":"وَعَمِلُوا","d":"waʿamilū","e":"and do"},{"b":"4.1","h":"4.58","c":"الصَّالِحَاتِ","d":"l-ṣāliḥāti","e":"righteous deeds"},{"b":"5.7","h":"6.44","c":"مِنْ","d":"min","e":"(out) of"},{"b":"7.2","h":"7.3","c":"فَضْلِهِ","d":"faḍlihi","e":"His Bounty"},{"b":"8.4","h":"10.1","c":"إِنَّهُ","d":"innahu","e":"Indeed He"},{"b":"10.0","h":"11.66","c":"لَا","d":"lā","e":"(does) not"},{"b":"10.4","h":"12.06","c":"يُحِبُّ","d":"yuḥibbu","e":"like"},{"b":"11.3","h":"13.08","c":"الْكَافِرِينَ","d":"l-kāfirīna","e":"the disbelievers"}],"a":{"g":"That He may reward those who have believed and done righteous deeds out of His bounty. Indeed, He does not like the disbelievers."}},"46":{"w":[{"b":"0.13","h":"0.4","c":"وَمِنْ","d":"wamin","e":"And among"},{"b":"0.69","h":"0.93","c":"ءَايَاتِهِ","d":"āyātihi","e":"His Signs"},{"b":"2.3","h":"3.94","c":"أَنْ","d":"an","e":"(is) that"},{"b":"4.6","h":"5.09","c":"يُرْسِلَ","d":"yur'sila","e":"He sends"},{"b":"5.4","h":"6.13","c":"الرِّيَاحَ","d":"l-riyāḥa","e":"the winds"},{"b":"6.4","h":"7.12","c":"مُبَشِّرَاتٍ","d":"mubashirātin","e":"(as) bearers of glad tidings"},{"b":"8.0","h":"9.6","c":"وَلِيُذِيقَكُمْ","d":"waliyudhīqakum","e":"and to let you taste"},{"b":"13.9","h":"12.26","c":"مِنْ","d":"min","e":"of"},{"b":"14","h":"12.34","c":"رَحْمَتِهِ","d":"raḥmatihi","e":"His Mercy"},{"b":"15.6","h":"14.27","c":"وَلِتَجْرِيَ","d":"walitajriya","e":"and that may sail"},{"b":"16.8","h":"15.79","c":"الْفُلْكُ","d":"l-ful'ku","e":"the ships"},{"b":"17.7","h":"16.89","c":"بِأَمْرِهِ","d":"bi-amrihi","e":"at His Command"},{"b":"18.9","h":"23.78","c":"وَلِتَبْتَغُوا","d":"walitabtaghū","e":"and that you may seek"},{"b":"20.","h":"25.73","c":"مِنْ","d":"min","e":"of"},{"b":"21.5","h":"26.66","c":"فَضْلِهِ","d":"faḍlihi","e":"His Bounty"},{"b":"22.6","h":"28.09","c":"وَلَعَلَّكُمْ","d":"walaʿallakum","e":"and that you may"},{"b":"24.0","h":"29.95","c":"تَشْكُرُونَ","d":"tashkurūna","e":"be grateful"}],"a":{"g":"And of His signs is that He sends the winds as bringers of good tidings and to let you taste His mercy and so the ships may sail at His command and so you may seek of His bounty, and perhaps you will be grateful."}},"47":{"w":[{"b":"0.24","h":"0.3","c":"وَلَقَدْ","d":"walaqad","e":"And verily"},{"b":"0.92","h":"1.14","c":"أَرْسَلْنَا","d":"arsalnā","e":"We sent"},{"b":"2.3","h":"2.87","c":"مِنْ","d":"min","e":"before you"},{"b":"3.4","h":"4.01","c":"قَبْلِكَ","d":"qablika","e":"before you"},{"b":"4.2","h":"5.09","c":"رُسُلًا","d":"rusulan","e":"Messengers"},{"b":"5.1","h":"6.18","c":"إِلَى","d":"ilā","e":"to"},{"b":"5.7","h":"6.94","c":"قَوْمِهِمْ","d":"qawmihim","e":"their people"},{"b":"6.7","h":"8.37","c":"فَجَاءُوهُمْ","d":"fajāūhum","e":"and they came to them"},{"b":"10.","h":"12.3","c":"بِالْبَيِّنَاتِ","d":"bil-bayināti","e":"with clear proofs"},{"b":"12.1","h":"14.36","c":"فَانْتَقَمْنَا","d":"fa-intaqamnā","e":"then We took retribution"},{"b":"14.0","h":"16.81","c":"مِنَ","d":"mina","e":"from"},{"b":"14.4","h":"17.26","c":"الَّذِينَ","d":"alladhīna","e":"those who"},{"b":"15.5","h":"18.57","c":"أَجْرَمُوا","d":"ajramū","e":"committed crimes"},{"b":"17.0","h":"22.9","c":"وَكَانَ","d":"wakāna","e":"And it was"},{"b":"17.8","h":"23.74","c":"حَقًّا","d":"ḥaqqan","e":"incumbent"},{"b":"18.6","h":"24.73","c":"عَلَيْنَا","d":"ʿalaynā","e":"upon Us"},{"b":"19.7","h":"26.25","c":"نَصْرُ","d":"naṣru","e":"(to) help"},{"b":"20.3","h":"27.06","c":"الْمُؤْمِنِينَ","d":"l-mu'minīna","e":"the believers"}],"a":{"g":"And We have already sent messengers before you to their peoples, and they came to them with clear evidences; then We took retribution from those who committed crimes, and incumbent upon Us was support of the believers."}},"48":{"w":[{"b":"0.32","h":"0.9","c":"اللَّهُ","d":"al-lahu","e":"Allah"},{"b":"1.2","h":"2.04","c":"الَّذِي","d":"alladhī","e":"(is) the One Who"},{"b":"2.1","h":"3.05","c":"يُرْسِلُ","d":"yur'silu","e":"sends"},{"b":"2.9","h":"4.1","c":"الرِّيَاحَ","d":"l-riyāḥa","e":"the winds"},{"b":"3.9","h":"5.21","c":"فَتُثِيرُ","d":"fatuthīru","e":"so they raise"},{"b":"4.9","h":"6.56","c":"سَحَابًا","d":"saḥāban","e":"(the) clouds"},{"b":"6.7","h":"8.48","c":"فَيَبْسُطُهُ","d":"fayabsuṭuhu","e":"then He spreads them"},{"b":"8.2","h":"10.54","c":"فِي","d":"fī","e":"in"},{"b":"8.5","h":"10.84","c":"السَّمَاءِ","d":"l-samāi","e":"the sky"},{"b":"15.3","h":"13.28","c":"كَيْفَ","d":"kayfa","e":"how"},{"b":"15.9","h":"14.22","c":"يَشَاءُ","d":"yashāu","e":"He wills"},{"b":"18.2","h":"16.47","c":"وَيَجْعَلُهُ","d":"wayajʿaluhu","e":"and He makes them"},{"b":"19.5","h":"18.5","c":"كِسَفًا","d":"kisafan","e":"fragments"},{"b":"20.9","h":"25.71","c":"فَتَرَى","d":"fatarā","e":"so you see"},{"b":"21.6","h":"26.59","c":"الْوَدْقَ","d":"l-wadqa","e":"the rain"},{"b":"22.4","h":"27.74","c":"يَخْرُجُ","d":"yakhruju","e":"coming forth"},{"b":"23.3","h":"28.9","c":"مِنْ","d":"min","e":"from"},{"b":"23.6","h":"29.26","c":"خِلَالِهِ","d":"khilālihi","e":"their midst"},{"b":"25.","h":"33.45","c":"فَإِذَا","d":"fa-idhā","e":"Then when"},{"b":"27.2","h":"33.99","c":"أَصَابَ","d":"aṣāba","e":"He causes it to fall on"},{"b":"28.1","h":"37.31","c":"بِهِ","d":"bihi","e":"He causes it to fall on"},{"b":"28.7","h":"38.29","c":"مَنْ","d":"man","e":"whom"},{"b":"29.9","h":"39.44","c":"يَشَاءُ","d":"yashāu","e":"He wills"},{"b":"32.1","h":"41.92","c":"مِنْ","d":"min","e":"of"},{"b":"32.4","h":"42.42","c":"عِبَادِهِ","d":"ʿibādihi","e":"His slaves"},{"b":"35.1","h":"45.38","c":"إِذَا","d":"idhā","e":"behold"},{"b":"35.6","h":"46.16","c":"هُمْ","d":"hum","e":"They"},{"b":"36.1","h":"46.82","c":"يَسْتَبْشِرُونَ","d":"yastabshirūna","e":"rejoice"}],"a":{"g":"It is Allah who sends the winds, and they stir the clouds and spread them in the sky however He wills, and He makes them fragments so you see the rain emerge from within them. And when He causes it to fall upon whom He wills of His servants, immediately they rejoice"}},"49":{"w":[{"b":"0.19","h":"0.21","c":"وَإِنْ","d":"wa-in","e":"And certainly"},{"b":"1.3","h":"1.53","c":"كَانُوا","d":"kānū","e":"they were"},{"b":"2.2","h":"3.01","c":"مِنْ","d":"min","e":"before"},{"b":"3.4","h":"3.97","c":"قَبْلِ","d":"qabli","e":"before"},{"b":"4.1","h":"4.85","c":"أَنْ","d":"an","e":"[that]"},{"b":"5.2","h":"6.18","c":"يُنَزَّلَ","d":"yunazzala","e":"it was sent down"},{"b":"6.2","h":"7.13","c":"عَلَيْهِمْ","d":"ʿalayhim","e":"upon them"},{"b":"7.9","h":"8.56","c":"مِنْ","d":"min","e":"[before it]"},{"b":"9.1","h":"10.35","c":"قَبْلِهِ","d":"qablihi","e":"[before it]"},{"b":"10.2","h":"11.87","c":"لَمُبْلِسِينَ","d":"lamub'lisīna","e":"surely in despair"}],"a":{"g":"Although they were, before it was sent down upon them - before that, in despair."}},"50":{"w":[{"b":"0.2","h":"0.95","c":"فَانْظُرْ","d":"fa-unẓur","e":"So look"},{"b":"1.7","h":"2.46","c":"إِلَى","d":"ilā","e":"at"},{"b":"3.7","h":"2.81","c":"ءَاثَارِ","d":"āthāri","e":"(the) effects"},{"b":"4.8","h":"5.91","c":"رَحْمَتِ","d":"raḥmati","e":"(of the) Mercy"},{"b":"5.8","h":"7.21","c":"اللَّهِ","d":"l-lahi","e":"(of) Allah"},{"b":"6.6","h":"8.26","c":"كَيْفَ","d":"kayfa","e":"how"},{"b":"7.2","h":"9.18","c":"يُحْيِي","d":"yuḥ'yī","e":"He gives life"},{"b":"7.9","h":"10.08","c":"الْأَرْضَ","d":"l-arḍa","e":"(to) the earth"},{"b":"8.7","h":"11.17","c":"بَعْدَ","d":"baʿda","e":"after"},{"b":"9.4","h":"12","c":"مَوْتِهَا","d":"mawtihā","e":"its death"},{"b":"11.1","h":"15.49","c":"إِنَّ","d":"inna","e":"Indeed"},{"b":"12.2","h":"16.63","c":"ذَلِكَ","d":"dhālika","e":"that"},{"b":"13.1","h":"17.78","c":"لَمُحْيِي","d":"lamuḥ'yī","e":"surely He (will) give life"},{"b":"14.0","h":"18.89","c":"الْمَوْتَى","d":"l-mawtā","e":"(to) the dead"},{"b":"15.6","h":"21.91","c":"وَهُوَ","d":"wahuwa","e":"And He"},{"b":"16.2","h":"22.48","c":"عَلَى","d":"ʿalā","e":"(is) on"},{"b":"16.8","h":"23.33","c":"كُلِّ","d":"kulli","e":"every"},{"b":"17.4","h":"24.2","c":"شَيْءٍ","d":"shayin","e":"thing"},{"b":"19.1","h":"25.92","c":"قَدِيرٌ","d":"qadīrun","e":"All-Powerful"}],"a":{"g":"So observe the effects of the mercy of Allah - how He gives life to the earth after its lifelessness. Indeed, that [same one] will give life to the dead, and He is over all things competent."}},"51":{"w":[{"b":"0.17","h":"0.65","c":"وَلَئِنْ","d":"wala-in","e":"But if"},{"b":"0.99","h":"1.53","c":"أَرْسَلْنَا","d":"arsalnā","e":"We sent"},{"b":"2.2","h":"3.22","c":"رِيحًا","d":"rīḥan","e":"a wind"},{"b":"3.9","h":"4.79","c":"فَرَأَوْهُ","d":"fara-awhu","e":"and they see it"},{"b":"5.0","h":"6.3","c":"مُصْفَرًّا","d":"muṣ'farran","e":"turn yellow"},{"b":"6.1","h":"7.59","c":"لَظَلُّوا","d":"laẓallū","e":"certainly they continue"},{"b":"7.3","h":"9.62","c":"مِنْ","d":"min","e":"after it"},{"b":"8.4","h":"10.62","c":"بَعْدِهِ","d":"baʿdihi","e":"after it"},{"b":"9.4","h":"12.24","c":"يَكْفُرُونَ","d":"yakfurūna","e":"(in) disbelief"}],"a":{"g":"But if We should send a [bad] wind and they saw [their crops] turned yellow, they would remain thereafter disbelievers."}},"52":{"w":[{"b":"0.11","h":"0.4","c":"فَإِنَّكَ","d":"fa-innaka","e":"So indeed, you"},{"b":"2.1","h":"2","c":"لَا","d":"lā","e":"(can) not"},{"b":"2.5","h":"2.52","c":"تُسْمِعُ","d":"tus'miʿu","e":"make the dead hear"},{"b":"3.4","h":"3.77","c":"الْمَوْتَى","d":"l-mawtā","e":"make the dead hear"},{"b":"4.5","h":"5.2","c":"وَلَا","d":"walā","e":"and not"},{"b":"5.1","h":"6.14","c":"تُسْمِعُ","d":"tus'miʿu","e":"make the deaf hear"},{"b":"6","h":"7.33","c":"الصُّمَّ","d":"l-ṣuma","e":"make the deaf hear"},{"b":"7.6","h":"9.01","c":"الدُّعَاءَ","d":"l-duʿāa","e":"the call"},{"b":"10.0","h":"11.41","c":"إِذَا","d":"idhā","e":"when"},{"b":"10.","h":"12.33","c":"وَلَّوْا","d":"wallaw","e":"they turn"},{"b":"11.7","h":"13.47","c":"مُدْبِرِينَ","d":"mud'birīna","e":"retreating"}],"a":{"g":"So indeed, you will not make the dead hear, nor will you make the deaf hear the call when they turn their backs, retreating."}},"53":{"w":[{"b":"0.16","h":"0.35","c":"وَمَا","d":"wamā","e":"And not"},{"b":"2.5","h":"2.53","c":"أَنْتَ","d":"anta","e":"you"},{"b":"3.9","h":"3.97","c":"بِهَادِ","d":"bihādi","e":"can guide"},{"b":"4.8","h":"5.17","c":"الْعُمْيِ","d":"l-ʿum'yi","e":"the blind"},{"b":"5.6","h":"6.35","c":"عَنْ","d":"ʿan","e":"from"},{"b":"6.7","h":"7.42","c":"ضَلَالَتِهِمْ","d":"ḍalālatihim","e":"their error"},{"b":"8.7","h":"12.35","c":"إِنْ","d":"in","e":"Not"},{"b":"9.9","h":"13.28","c":"تُسْمِعُ","d":"tus'miʿu","e":"you can make hear"},{"b":"10.8","h":"14.56","c":"إِلَّا","d":"illā","e":"except"},{"b":"11.7","h":"15.81","c":"مَنْ","d":"man","e":"(those) who"},{"b":"12.6","h":"16.86","c":"يُؤْمِنُ","d":"yu'minu","e":"believe"},{"b":"13.4","h":"18.03","c":"بِءَايَاتِنَا","d":"biāyātinā","e":"in Our Verses"},{"b":"15.1","h":"20.64","c":"فَهُمْ","d":"fahum","e":"so they"},{"b":"16.3","h":"22.26","c":"مُسْلِمُونَ","d":"mus'limūna","e":"surrender"}],"a":{"g":"And you cannot guide the blind away from their error. You will only make hear those who believe in Our verses so they are Muslims [in submission to Allah]."}},"54":{"w":[{"b":"0.21","h":"1.1","c":"اللَّهُ","d":"al-lahu","e":"Allah"},{"b":"1.1","h":"2.42","c":"الَّذِي","d":"alladhī","e":"(is) the One Who"},{"b":"1.8","h":"3.49","c":"خَلَقَكُمْ","d":"khalaqakum","e":"created you"},{"b":"3.7","h":"4.95","c":"مِنْ","d":"min","e":"from"},{"b":"4.7","h":"6.88","c":"ضَعْفٍ","d":"ḍaʿfin","e":"weakness"},{"b":"6.4","h":"8.64","c":"ثُمَّ","d":"thumma","e":"then"},{"b":"7.5","h":"9.96","c":"جَعَلَ","d":"jaʿala","e":"made"},{"b":"8.1","h":"10.92","c":"مِنْ","d":"min","e":"after"},{"b":"9.0","h":"11.94","c":"بَعْدِ","d":"baʿdi","e":"after"},{"b":"9.6","h":"12.84","c":"ضَعْفٍ","d":"ḍaʿfin","e":"weakness"},{"b":"11.2","h":"14.87","c":"قُوَّةً","d":"quwwatan","e":"strength"},{"b":"13.3","h":"18.65","c":"ثُمَّ","d":"thumma","e":"then"},{"b":"14.4","h":"19.8","c":"جَعَلَ","d":"jaʿala","e":"made"},{"b":"15.1","h":"20.78","c":"مِنْ","d":"min","e":"after"},{"b":"16.0","h":"21.77","c":"بَعْدِ","d":"baʿdi","e":"after"},{"b":"16.6","h":"31.36","c":"قُوَّةٍ","d":"quwwatin","e":"strength"},{"b":"18.5","h":"33.59","c":"ضَعْفًا","d":"ḍaʿfan","e":"weakness"},{"b":"19.1","h":"35.61","c":"وَشَيْبَةً","d":"washaybatan","e":"and gray hair"},{"b":"21.6","h":"39.5","c":"يَخْلُقُ","d":"yakhluqu","e":"He creates"},{"b":"22.4","h":"40.65","c":"مَا","d":"mā","e":"what"},{"b":"22.8","h":"41.35","c":"يَشَاءُ","d":"yashāu","e":"He wills"},{"b":"26.4","h":"45.95","c":"وَهُوَ","d":"wahuwa","e":"and He"},{"b":"27.0","h":"46.79","c":"الْعَلِيمُ","d":"l-ʿalīmu","e":"(is) the All-Knower"},{"b":"28.1","h":"48.46","c":"الْقَدِيرُ","d":"l-qadīru","e":"the All-Powerful"}],"a":{"g":"Allah is the one who created you from weakness, then made after weakness strength, then made after strength weakness and white hair. He creates what He wills, and He is the Knowing, the Competent."}},"55":{"w":[{"b":"0.15","h":"0.15","c":"وَيَوْمَ","d":"wayawma","e":"And (the) Day"},{"b":"0.86","h":"1.14","c":"تَقُومُ","d":"taqūmu","e":"will (be) established"},{"b":"1.7","h":"2.49","c":"السَّاعَةُ","d":"l-sāʿatu","e":"the Hour"},{"b":"2.7","h":"4.3","c":"يُقْسِمُ","d":"yuq'simu","e":"will swear"},{"b":"3.6","h":"5.6","c":"الْمُجْرِمُونَ","d":"l-muj'rimūna","e":"the criminals"},{"b":"5.0","h":"7.75","c":"مَا","d":"mā","e":"not"},{"b":"5.4","h":"8.43","c":"لَبِثُوا","d":"labithū","e":"they remained"},{"b":"6.2","h":"9.84","c":"غَيْرَ","d":"ghayra","e":"but"},{"b":"6.8","h":"10.81","c":"سَاعَةٍ","d":"sāʿatin","e":"an hour"},{"b":"8.0","h":"14.55","c":"كَذَلِكَ","d":"kadhālika","e":"Thus"},{"b":"9.0","h":"15.95","c":"كَانُوا","d":"kānū","e":"they were"},{"b":"9.8","h":"17.51","c":"يُؤْفَكُونَ","d":"yu'fakūna","e":"deluded"}],"a":{"g":"And the Day the Hour appears the criminals will swear they had remained but an hour. Thus they were deluded."}},"56":{"w":[{"b":"0.23","h":"0.9","c":"وَقَالَ","d":"waqāla","e":"But will say"},{"b":"1","h":"2.01","c":"الَّذِينَ","d":"alladhīna","e":"those who"},{"b":"2.0","h":"3.52","c":"أُوتُوا","d":"ūtū","e":"were given"},{"b":"2.7","h":"4.62","c":"الْعِلْمَ","d":"l-ʿil'ma","e":"the knowledge"},{"b":"3.5","h":"5.85","c":"وَالْإِيمَانَ","d":"wal-īmāna","e":"and the faith"},{"b":"4.9","h":"8.19","c":"لَقَدْ","d":"laqad","e":"Verily"},{"b":"5.4","h":"9.07","c":"لَبِثْتُمْ","d":"labith'tum","e":"you remained"},{"b":"6.5","h":"10.7","c":"فِي","d":"fī","e":"by"},{"b":"6.9","h":"11.4","c":"كِتَابِ","d":"kitābi","e":"(the) Decree"},{"b":"7.9","h":"12.91","c":"اللَّهِ","d":"l-lahi","e":"(of) Allah"},{"b":"8.7","h":"14.15","c":"إِلَى","d":"ilā","e":"until"},{"b":"9.2","h":"15.12","c":"يَوْمِ","d":"yawmi","e":"(the) Day"},{"b":"9.8","h":"16.27","c":"الْبَعْثِ","d":"l-baʿthi","e":"(of) Resurrection"},{"b":"11.1","h":"19.65","c":"فَهَذَا","d":"fahādhā","e":"And this"},{"b":"12.1","h":"21.22","c":"يَوْمُ","d":"yawmu","e":"(is the) Day"},{"b":"12.","h":"22.32","c":"الْبَعْثِ","d":"l-baʿthi","e":"(of) the Resurrection"},{"b":"13.7","h":"23.73","c":"وَلَكِنَّكُمْ","d":"walākinnakum","e":"but you"},{"b":"16.0","h":"27.07","c":"كُنْتُمْ","d":"kuntum","e":"were"},{"b":"17.8","h":"29.09","c":"لَا","d":"lā","e":"not"},{"b":"18.1","h":"29.79","c":"تَعْلَمُونَ","d":"taʿlamūna","e":"knowing"}],"a":{"g":"But those who were given knowledge and faith will say, \"You remained the extent of Allah 's decree until the Day of Resurrection, and this is the Day of Resurrection, but you did not used to know.\""}},"57":{"w":[{"b":"0.25","h":"0.75","c":"فَيَوْمَئِذٍ","d":"fayawma-idhin","e":"So that Day"},{"b":"1.4","h":"2.46","c":"لَا","d":"lā","e":"not"},{"b":"1.9","h":"3.49","c":"يَنْفَعُ","d":"yanfaʿu","e":"will profit"},{"b":"3.6","h":"5.13","c":"الَّذِينَ","d":"alladhīna","e":"those who"},{"b":"4.7","h":"6.59","c":"ظَلَمُوا","d":"ẓalamū","e":"wronged"},{"b":"5.6","h":"8","c":"مَعْذِرَتُهُمْ","d":"maʿdhiratuhum","e":"their excuses"},{"b":"7.0","h":"10.26","c":"وَلَا","d":"walā","e":"and not"},{"b":"7.6","h":"11.22","c":"هُمْ","d":"hum","e":"they"},{"b":"8.1","h":"12.02","c":"يُسْتَعْتَبُونَ","d":"yus'taʿtabūna","e":"will be allowed to make amends"}],"a":{"g":"So that Day, their excuse will not benefit those who wronged, nor will they be asked to appease [Allah]."}},"58":{"w":[{"b":"0.22","h":"1.05","c":"وَلَقَدْ","d":"walaqad","e":"And verily"},{"b":"1.0","h":"1.98","c":"ضَرَبْنَا","d":"ḍarabnā","e":"We (have) set forth"},{"b":"2.1","h":"3.67","c":"لِلنَّاسِ","d":"lilnnāsi","e":"for mankind"},{"b":"3.7","h":"5.68","c":"فِي","d":"fī","e":"in"},{"b":"4.2","h":"6.37","c":"هَذَا","d":"hādhā","e":"this"},{"b":"4.8","h":"7.52","c":"الْقُرْءَانِ","d":"l-qur'āni","e":"[the] Quran"},{"b":"6.1","h":"9.76","c":"مِنْ","d":"min","e":"of"},{"b":"7.1","h":"10.83","c":"كُلِّ","d":"kulli","e":"every"},{"b":"7.8","h":"11.94","c":"مَثَلٍ","d":"mathalin","e":"example"},{"b":"8.8","h":"16.21","c":"وَلَئِنْ","d":"wala-in","e":"But if"},{"b":"10.3","h":"17.89","c":"جِئْتَهُمْ","d":"ji'tahum","e":"you bring them"},{"b":"12.2","h":"20.02","c":"بِءَايَةٍ","d":"biāyatin","e":"a sign"},{"b":"13.3","h":"21.86","c":"لَيَقُولَنَّ","d":"layaqūlanna","e":"surely will say"},{"b":"15.","h":"25.03","c":"الَّذِينَ","d":"alladhīna","e":"those who"},{"b":"16.6","h":"26.67","c":"كَفَرُوا","d":"kafarū","e":"disbelieve"},{"b":"19","h":"29.08","c":"إِنْ","d":"in","e":"Not"},{"b":"19.3","h":"29.76","c":"أَنْتُمْ","d":"antum","e":"you"},{"b":"20.6","h":"31.71","c":"إِلَّا","d":"illā","e":"(are) except"},{"b":"21.4","h":"33.15","c":"مُبْطِلُونَ","d":"mub'ṭilūna","e":"falsifiers"}],"a":{"g":"And We have certainly presented to the people in this Qur'an from every [kind of] example. But, [O Muhammad], if you should bring them a sign, the disbelievers will surely say, \"You [believers] are but falsifiers.\""}},"59":{"w":[{"b":"0.16","h":"0.35","c":"كَذَلِكَ","d":"kadhālika","e":"Thus"},{"b":"1.1","h":"1.74","c":"يَطْبَعُ","d":"yaṭbaʿu","e":"Allah seals"},{"b":"1.9","h":"3.05","c":"اللَّهُ","d":"l-lahu","e":"Allah seals"},{"b":"2.7","h":"4.19","c":"عَلَى","d":"ʿalā","e":"[on]"},{"b":"3.3","h":"5.27","c":"قُلُوبِ","d":"qulūbi","e":"(the) hearts"},{"b":"4.3","h":"6.67","c":"الَّذِينَ","d":"alladhīna","e":"(of) those who"},{"b":"5.3","h":"8.25","c":"لَا","d":"lā","e":"(do) not"},{"b":"5.7","h":"8.97","c":"يَعْلَمُونَ","d":"yaʿlamūna","e":"know"}],"a":{"g":"Thus does Allah seal the hearts of those who do not know."}},"60":{"w":[{"b":"0.08","h":"1","c":"فَاصْبِرْ","d":"fa-iṣ'bir","e":"So be patient"},{"b":"0.85","h":"2.24","c":"إِنَّ","d":"inna","e":"Indeed"},{"b":"2.6","h":"3.67","c":"وَعْدَ","d":"waʿda","e":"(the) Promise"},{"b":"3.3","h":"4.75","c":"اللَّهِ","d":"l-lahi","e":"(of) Allah"},{"b":"4.1","h":"6.2","c":"حَقٌّ","d":"ḥaqqun","e":"(is) true"},{"b":"5.1","h":"9.1","c":"وَلَا","d":"walā","e":"And (let) not"},{"b":"5.7","h":"9.97","c":"يَسْتَخِفَّنَّكَ","d":"yastakhiffannaka","e":"take you in light estimation"},{"b":"8.5","h":"13.42","c":"الَّذِينَ","d":"alladhīna","e":"those who"},{"b":"9.7","h":"15.12","c":"لَا","d":"lā","e":"(are) not"},{"b":"10.1","h":"15.91","c":"يُوقِنُونَ","d":"yūqinūna","e":"certain in faith"}],"a":{"g":"So be patient. Indeed, the promise of Allah is truth. And let them not disquiet you who are not certain [in faith]."}}}